cn_stock_src/__init__.py
cn_stock_src/cn_stock_base.py
cn_stock_src/cn_stock_util.py
cn_stock_src/test_cn_stock_util.py
cn_stock_src/netease/__init__.py
cn_stock_src/netease/test_netease_stock.py
cn_stock_src/sina/__init__.py
cn_stock_src/sina/sina_stock.py
cn_stock_src/sina/sina_stock_info.py
cn_stock_src/sina/test_sina_stock.py
cn_stock_src/tdx/__init__.py
cn_stock_src/tdx/test_tdx.py
cn_stock_src/yahoo/__init__.py
cn_stock_src/yahoo/test_yahoo_data.py
cn_stock_src-0.1.8.dist-info/DESCRIPTION.rst
cn_stock_src-0.1.8.dist-info/METADATA
cn_stock_src-0.1.8.dist-info/RECORD
cn_stock_src-0.1.8.dist-info/WHEEL
cn_stock_src-0.1.8.dist-info/metadata.json
cn_stock_src-0.1.8.dist-info/pbr.json
cn_stock_src-0.1.8.dist-info/top_level.txt
test/__init__.py
test/test_cn_stock_util.py
test/netease/__init__.py
test/netease/test_netease.py
test/sina/__init__.py
test/sina/test_sina_stock.py
test/tdx/__init__.py
test/tdx/test_tdx.py
test/yahoo/__init__.py
test/yahoo/test_yahoo_data.py
