Metadata-Version: 2.0
Name: cn-stock-src
Version: 0.1.8
Summary: Utility for retrieving basic China stock data from different sources.
Home-page: http://github.com/jealous/cn_stock_src
Author: Cedric Zhuang
Author-email: jealous@163.com
License: BSD
Keywords: Stock data retriever for China stock market.
Platform: any
Classifier: Programming Language :: Python
Classifier: Programming Language :: Python :: 2.7
Classifier: Programming Language :: Python :: 3.4
Classifier: Programming Language :: Python :: 3.5
Classifier: Programming Language :: Python :: Implementation :: CPython
Classifier: Natural Language :: English
Classifier: Intended Audience :: Developers
Classifier: Intended Audience :: Financial and Insurance Industry
Classifier: Operating System :: OS Independent
Classifier: Development Status :: 4 - Beta
Classifier: Topic :: Utilities
Classifier: License :: OSI Approved :: BSD License
Requires-Dist: int-date (>=0.1.7)
Requires-Dist: pandas (>=0.15.2)
Requires-Dist: requests (>=2.7.0)
Requires-Dist: six (>=1.9.0)
